rq_gevent_worker.py
setup.py
rq_gevent_worker.egg-info/PKG-INFO
rq_gevent_worker.egg-info/SOURCES.txt
rq_gevent_worker.egg-info/dependency_links.txt
rq_gevent_worker.egg-info/entry_points.txt
rq_gevent_worker.egg-info/requires.txt
rq_gevent_worker.egg-info/top_level.txt