Metadata-Version: 1.0
Name: rq-gevent-worker
Version: 0.1.6
Summary: Implement a new worker based on gevent
Home-page: https://github.com/zhangliyong/rq-gevent-worker
Author: Lyon Zhang
Author-email: lyzhang87@gmail.com
License: BSD
Platform: UNKNOWN
